pycoloram.py
pycoloram-1.0.3.dist-info/WHEEL
pycoloram-1.0.3.dist-info/METADATA
pycoloram-1.0.3.dist-info/RECORD
